codebreaker/__init__.py
codebreaker/command_line.py
codebreaker/decompile_replays.py
codebreaker/analysis/PROTOBUF_VERSION
codebreaker/analysis/__init__.py
codebreaker/analysis/analysis_manager.py
codebreaker/analysis/cleaner/__init__.py
codebreaker/analysis/cleaner/cleaner.py
codebreaker/analysis/cleaner/frame_cleaner.py
codebreaker/analysis/constants/__init__.py
codebreaker/analysis/constants/basic_math.py
codebreaker/analysis/constants/dropshot.py
codebreaker/analysis/constants/field_constants.py
codebreaker/analysis/constants/playlist.py
codebreaker/analysis/events/__init__.py
codebreaker/analysis/events/carry_detection.py
codebreaker/analysis/events/event_creator.py
codebreaker/analysis/events/boost_pad_detection/__init__.py
codebreaker/analysis/events/boost_pad_detection/pickup_analysis.py
codebreaker/analysis/events/bump_detection/__init__.py
codebreaker/analysis/events/bump_detection/bump_analysis.py
codebreaker/analysis/events/dropshot/__init__.py
codebreaker/analysis/events/dropshot/ball.py
codebreaker/analysis/events/dropshot/damage.py
codebreaker/analysis/events/fifty_fifty/__init__.py
codebreaker/analysis/events/fifty_fifty/fifty_analysis.py
codebreaker/analysis/events/hit_detection/__init__.py
codebreaker/analysis/events/hit_detection/base_hit.py
codebreaker/analysis/events/hit_detection/hit_analysis.py
"codebreaker/analysis/events/hit_detection/hitbox/Vehicle Specifications v1.39 - Hitboxes, Handling.xlsx"
codebreaker/analysis/events/hit_detection/hitbox/__init__.py
codebreaker/analysis/events/hit_detection/hitbox/car.py
codebreaker/analysis/events/hit_detection/hitbox/hitbox.py
codebreaker/analysis/events/hit_pressure/__init__.py
codebreaker/analysis/events/hit_pressure/pressure_analysis.py
codebreaker/analysis/events/kickoff_detection/__init__.py
codebreaker/analysis/events/kickoff_detection/kickoff_analysis.py
codebreaker/analysis/saltie_game/__init__.py
codebreaker/analysis/saltie_game/saltie_game.py
codebreaker-0.7.9.dist-info/LICENSE
codebreaker-0.7.9.dist-info/METADATA
codebreaker-0.7.9.dist-info/NOTICE
codebreaker-0.7.9.dist-info/WHEEL
codebreaker-0.7.9.dist-info/entry_points.txt
codebreaker-0.7.9.dist-info/top_level.txt
codebreaker-0.7.9.dist-info/RECORD
